{
  "type": "minecraft:chest",
  "pools": [
    {
      "rolls": 1,
      "entries": [
        {
          "type": "minecraft:item",
          "name": "minecraft:diamond",
          "functions": [
            {
              "function": "minecraft:set_count",
              "count": {
                "min": 5,
                "max": 8
              }
            }
          ]
        }
      ]
    },
    {
      "rolls": 3,
      "entries": [
        {
          "type": "minecraft:item",
          "weight": 1,
          "name": "minecraft:experience_bottle",
          "functions": [
            {
              "function": "minecraft:set_count",
              "count": {
                "min": 8,
                "max": 12
              }
            }
          ]
        },
        {
          "type": "minecraft:item",
          "weight": 1,
          "name": "minecraft:golden_apple"
        }
      ]
    },
    {
      "rolls": 1,
      "entries": [
        {
          "type": "minecraft:item",
          "weight": 1,
          "name": "minecraft:wither_skeleton_skull"
        },
        {
          "type": "minecraft:item",
          "weight": 1,
          "name": "minecraft:netherite_ingot"
        },
        {
          "type": "minecraft:item",
          "weight": 1,
          "name": "hexfortress:obsidian_talisman"
        },
        {
          "type": "minecraft:item",
          "weight": 1,
          "name": "hexfortress:witherite_shears"
        },
        {
          "type": "minecraft:item",
          "weight": 1,
          "name": "hexfortress:wither_skull_fragment",
          "functions": [
            {
              "function": "minecraft:set_count",
              "count": {
                "min": 3,
                "max": 5
              }
            }
          ]
        },
        {
          "type": "minecraft:item",
          "name": "hexfortress:fragment_of_greed"
        }
      ]
    }
  ]
}
